piedrilldown/__init__.py
piedrilldown/core.py
piedrilldown-1.0.0.dist-info/licenses/LICENSE
piedrilldown-1.0.0.dist-info/METADATA
piedrilldown-1.0.0.dist-info/WHEEL
piedrilldown-1.0.0.dist-info/top_level.txt
piedrilldown-1.0.0.dist-info/RECORD
