Metadata-Version: 2.4
Name: piedrilldown
Version: 1.0.0
Summary: A Python package for creating professional Bar-of-Pie and Pie-of-Pie charts with drill-down visualizations
Home-page: https://github.com/yourusername/piedrilldown
Author: Your Name
Author-email: Your Name <your.email@example.com>
Maintainer-email: Your Name <your.email@example.com>
License: MIT
Project-URL: Homepage, https://github.com/yourusername/piedrilldown
Project-URL: Documentation, https://github.com/yourusername/piedrilldown#readme
Project-URL: Repository, https://github.com/yourusername/piedrilldown
Project-URL: Issues, https://github.com/yourusername/piedrilldown/issues
Project-URL: Changelog, https://github.com/yourusername/piedrilldown/blob/main/CHANGELOG.md
Keywords: visualization,charts,pie chart,bar chart,drilldown,matplotlib,data visualization,plotting
Classifier: Development Status :: 4 - Beta
Classifier: Intended Audience :: Science/Research
Classifier: Intended Audience :: Developers
Classifier: Intended Audience :: Education
Classifier: License :: OSI Approved :: MIT License
Classifier: Operating System :: OS Independent
Classifier: Programming Language :: Python :: 3
Classifier: Programming Language :: Python :: 3.7
Classifier: Programming Language :: Python :: 3.8
Classifier: Programming Language :: Python :: 3.9
Classifier: Programming Language :: Python :: 3.10
Classifier: Programming Language :: Python :: 3.11
Classifier: Programming Language :: Python :: 3.12
Classifier: Topic :: Scientific/Engineering :: Visualization
Classifier: Topic :: Multimedia :: Graphics :: Presentation
Requires-Python: >=3.7
License-File: LICENSE
Requires-Dist: matplotlib>=3.0.0
Requires-Dist: numpy>=1.15.0
Provides-Extra: dev
Requires-Dist: pytest>=6.0.0; extra == "dev"
Requires-Dist: black; extra == "dev"
Requires-Dist: flake8; extra == "dev"
Requires-Dist: build; extra == "dev"
Requires-Dist: twine; extra == "dev"
Dynamic: author
Dynamic: home-page
Dynamic: license-file
Dynamic: requires-python
